spiderkit/__init__.py
spiderkit/config/__init__.py
spiderkit/config/settings.py
spiderkit/crypto/__init__.py
spiderkit/crypto/asymmetric.py
spiderkit/crypto/symmetric.py
spiderkit/downloader/__init__.py
spiderkit/downloader/async_http_downloader.py
spiderkit/downloader/m3u8_downloader.py
spiderkit/storage/__init__.py
spiderkit/storage/file_storage.py
spiderkit/utils/__init__.py
spiderkit/utils/common_utils.py
spiderkit/utils/font_parser.py
spiderkit/utils/hash_utils.py
spiderkit-0.1.9.dist-info/METADATA
spiderkit-0.1.9.dist-info/WHEEL
spiderkit-0.1.9.dist-info/RECORD
