Metadata-Version: 2.4
Name: spiderkit
Version: 0.1.9
Summary: 一个面向爬虫与数据处理场景的 Python 工具包, 覆盖加密解密, 数据存储, 异步下载, 字体解析和哈希工具
Project-URL: Homepage, https://github.com/dawn0608/spiderkit
Author-email: Dawn <3439972272@qq.com>
License: MIT
Keywords: aes,anti-crawler,async,crawler,cryptography,data-processing,des,download,encryption,font-parser,hash,m3u8,rsa,scraping,spider,storage
Classifier: Development Status :: 4 - Beta
Classifier: Intended Audience :: Developers
Classifier: License :: OSI Approved :: MIT License
Classifier: Operating System :: OS Independent
Classifier: Programming Language :: Python :: 3
Classifier: Programming Language :: Python :: 3.11
Classifier: Programming Language :: Python :: 3.12
Classifier: Programming Language :: Python :: 3.13
Classifier: Topic :: Internet :: WWW/HTTP
Classifier: Topic :: Security :: Cryptography
Classifier: Topic :: Software Development :: Libraries :: Python Modules
Classifier: Topic :: Utilities
Requires-Python: >=3.11
Requires-Dist: aiofiles>=23.0.0
Requires-Dist: aiohttp>=3.8.0
Requires-Dist: ddddocr>=1.4.0
Requires-Dist: fonttools>=4.40.0
Requires-Dist: inflection>=0.5.1
Requires-Dist: loguru>=0.7.0
Requires-Dist: m3u8>=3.5.0
Requires-Dist: pillow>=10.0.0
Requires-Dist: pycryptodome>=3.18.0
Requires-Dist: tqdm>=4.65.0
